infer_license/__init__.py
infer_license/api.py
infer_license/cmdline.py
infer_license/py.typed
infer_license/types.py
infer_license/licenses/AGPL-3.0-or-later.txt
infer_license/licenses/Apache-2.0.txt
infer_license/licenses/BSD-2-Clause.txt
infer_license/licenses/BSD-3-Clause.txt
infer_license/licenses/CC-BY-4.0.txt
infer_license/licenses/GPL-2.0-or-later.txt
infer_license/licenses/GPL-3.0-or-later.txt
infer_license/licenses/ISC.txt
infer_license/licenses/LGPL-2.0-or-later.txt
infer_license/licenses/LGPL-2.1-or-later.txt
infer_license/licenses/LGPL-3.0-or-later.txt
infer_license/licenses/MIT-0.txt
infer_license/licenses/MIT.txt
infer_license/licenses/Python-2.0.txt
infer_license/licenses/X11.txt
infer_license/licenses/__init__.py
infer_license/tests/__init__.py
infer_license/tests/__main__.py
infer_license/tests/api.py
infer_license/tests/cmdline.py
infer_license-0.2.0.dist-info/LICENSE
infer_license-0.2.0.dist-info/METADATA
infer_license-0.2.0.dist-info/WHEEL
infer_license-0.2.0.dist-info/entry_points.txt
infer_license-0.2.0.dist-info/top_level.txt
infer_license-0.2.0.dist-info/RECORD
