Metadata-Version: 2.1
Name: infer-license
Version: 0.2.0
Summary: A script to guess licenses based on text
Home-page: https://github.com/python-packaging/infer-license/
Author: Tim Hatch
Author-email: tim@timhatch.com
License: MIT
Requires-Python: >=3.10
License-File: LICENSE
Requires-Dist: dataclasses >=0.7 ; python_version < "3.7"
Requires-Dist: importlib-resources ; python_version < "3.7"
Provides-Extra: dev
Requires-Dist: black ==23.12.1 ; extra == 'dev'
Requires-Dist: checkdeps ==0.0.2 ; extra == 'dev'
Requires-Dist: flake8 ==7.0.0 ; extra == 'dev'
Requires-Dist: mypy ==1.8.0 ; extra == 'dev'
Requires-Dist: tox ==4.12.1 ; extra == 'dev'
Requires-Dist: twine ==4.0.2 ; extra == 'dev'
Requires-Dist: ufmt ==2.3.0 ; extra == 'dev'
Requires-Dist: usort ==1.0.7 ; extra == 'dev'
Requires-Dist: wheel ==0.42.0 ; extra == 'dev'
Provides-Extra: test
Requires-Dist: coverage >=6 ; extra == 'test'
